bluesocket/__init__.py
bluesocket-0.0.1.dist-info/LICENSE
bluesocket-0.0.1.dist-info/METADATA
bluesocket-0.0.1.dist-info/WHEEL
bluesocket-0.0.1.dist-info/top_level.txt
bluesocket-0.0.1.dist-info/RECORD
