Metadata-Version: 2.1
Name: bluesocket
Version: 0.0.1
Summary: Django Channels logger
Home-page: https://github.com/3megawatt/bluesocket
Author: Emin Bugra Saral
Author-email: eminbugrasaral@me.com
License: UNKNOWN
Platform: UNKNOWN
Classifier: Programming Language :: Python :: 3
Classifier: Intended Audience :: Developers
Classifier: License :: OSI Approved :: MIT License
Classifier: Operating System :: OS Independent
Requires-Dist: channels
